labs/lab2/LAB-02_codes (0508)/lab2.v
// pipelined fast multiplier
module mult_fast(
	output reg[7:0] P,  // product
	input[3:0] A, B,    // multiplicand and multiplier
	input clk		    // clock (posedge)
	);
	// stage 0 (input)
	reg[3:0] a_s0, b_s0;
	always @(posedge clk) begin
		a_s0 <= A;
		b_s0 <= B;
	end
	// stage 1
	wire[3:0] pp0 = a_s0 & {4{b_s0[0]}}; // ignore the delays of AND gates
	wire[4:1] pp1 = a_s0 & {4{b_s0[1]}}; // ignore the delays of AND gates
	wire[5:2] pp2 = a_s0 & {4{b_s0[2]}}; // ignore the delays of AND gates
	wire[6:3] pp3 = a_s0 & {4{b_s0[3]}}; // ignore the delays of AND gates
	reg[5:1] sum1;
	always @(pp0, pp1)
		sum1[5:1] <= #7 pp0[3:1] + pp1[4:1]; // delay of the 4-bit adder
	reg[7:3] sum3;
	always @(pp2, pp3)
		sum3[7:3] <= #7 pp2[5:3] + pp3[6:3]; // delay of the 4-bit adder
	reg[5:0] sum1_s1;
	reg[7:2] sum3_s1;
	always @(posedge clk) begin
		sum1_s1 <= {sum1, pp0[0]};
		sum3_s1 <= {sum3, pp2[2]};
	end
	// stage 2 (outout)
	reg[7:2] sum2;
	always @(sum1_s1, sum3_s1)
		sum2[7:2] <= #8 sum1_s1[5:2] + sum3_s1[7:2]; // delay of the 6-bit adder
	always @(posedge clk) begin
		P <= {sum2, sum1_s1[1:0]};
	end
endmodule

// test bench
module mult_tb();
	// dump
	initial begin
		$dumpfile("lab2.vcd");
		$dumpvars(0, mult_tb);
	end
	// clock cycle = 10 ticks
	reg clock = 1;
	always
		#5 clock <= ~clock;
	// multiplier
	reg[3:0] A, B;
	wire[7:0] P;
	reg[7:0] P_ref;
	mult_fast mult(P, A, B, clock);
	always @(posedge clock)
		P_ref <= #20 A*B;
	// loop through all possible inputs
	integer i;
	initial begin
		#9;
		for(i=0; i<256; i=i+1) begin
			{A, B} <= i;
			#10;
		end
		#21 $finish;
	end
	// check if the products are correct
	reg[3:0] A_old, B_old;
	always @(posedge clock) begin
		#1
		if(P_ref!=P && i>=2) begin
			A_old = (i-2)/16;
			B_old = (i-2)%16;
			$display("Product is wrong when A=%b, B=%b.", A_old, B_old);
			$display("P_ref: %b.", P_ref);
			$display("P    : %b.", P);
			#9 $finish;
		end
	end
endmodule

labs/lab2/LAB-02_codes (0508)/lab2.vcd
$date
	Tue May 16 12:06:16 2023
$end
$version
	Icarus Verilog
$end
$timescale
	1s
$end
$scope module mult_tb $end
$var wire 8 ! P [7:0] $end
$var reg 4 " A [3:0] $end
$var reg 4 # A_old [3:0] $end
$var reg 4 $ B [3:0] $end
$var reg 4 % B_old [3:0] $end
$var reg 8 & P_ref [7:0] $end
$var reg 1 ' clock $end
$var integer 32 ( i [31:0] $end
$scope module mult $end
$var wire 4 ) A [3:0] $end
$var wire 4 * B [3:0] $end
$var wire 1 ' clk $end
$var wire 4 + pp0 [3:0] $end
$var wire 4 , pp1 [4:1] $end
$var wire 4 - pp2 [5:2] $end
$var wire 4 . pp3 [6:3] $end
$var reg 8 / P [7:0] $end
$var reg 4 0 a_s0 [3:0] $end
$var reg 4 1 b_s0 [3:0] $end
$var reg 5 2 sum1 [5:1] $end
$var reg 6 3 sum1_s1 [5:0] $end
$var reg 6 4 sum2 [7:2] $end
$var reg 5 5 sum3 [7:3] $end
$var reg 6 6 sum3_s1 [7:2] $end
$upscope $end
$upscope $end
$enddefinitions $end
#0
$dumpvars
bx 6
bx 5
bx 4
bx 3
bx 2
bx 1
bx 0
bx /
bx .
bx -
bx ,
bx +
bx *
bx )
bx (
1'
bx &
bx %
bx $
bx #
bx "
bx !
$end
#5
0'
#9
b0 "
b0 )
b0 $
b0 *
b0 (
#10
b0 .
b0 -
b0 ,
b0 +
b0 1
b0 0
1'
#15
0'
#17
b0 5
b0 2
#19
b1 $
b1 *
b1 (
#20
b1 1
b0 6
b0 3
1'
#25
0'
#28
b0 4
#29
b10 $
b10 *
b10 (
#30
b0 !
b0 /
b10 1
1'
b0 &
#35
0'
#39
b11 $
b11 *
b11 (
#40
b11 1
1'
#45
0'
#49
b100 $
b100 *
b100 (
#50
b100 1
1'
#55
0'
#59
b101 $
b101 *
b101 (
#60
b101 1
1'
#65
0'
#69
b110 $
b110 *
b110 (
#70
b110 1
1'
#75
0'
#79
b111 $
b111 *
b111 (
#80
b111 1
1'
#85
0'
#89
b1000 $
b1000 *
b1000 (
#90
b1000 1
1'
#95
0'
#99
b1001 $
b1001 *
b1001 (
#100
b1001 1
1'
#105
0'
#109
b1010 $
b1010 *
b1010 (
#110
b1010 1
1'
#115
0'
#119
b1011 $
b1011 *
b1011 (
#120
b1011 1
1'
#125
0'
#129
b1100 $
b1100 *
b1100 (
#130
b1100 1
1'
#135
0'
#139
b1101 $
b1101 *
b1101 (
#140
b1101 1
1'
#145
0'
#149
b1110 $
b1110 *
b1110 (
#150
b1110 1
1'
#155
0'
#159
b1111 $
b1111 *
b1111 (
#160
b1111 1
1'
#165
0'
#169
b1 "
b1 )
b0 $
b0 *
b10000 (
#170
b0 .
b0 -
b0 ,
b0 +
b0 1
b1 0
1'
#175
0'
#177
b0 5
b0 2
#179
b1 $
b1 *
b10001 (
#180
b1 +
b1 1
1'
#185
0'
#189
b10 $
b10 *
b10010 (
#190
b0 +
b1 ,
b1 3
b10 1
1'
#195
0'
#197
b1 2
#199
b11 $
b11 *
b10011 (
#200
b1 +
b11 1
b10 3
b1 !
b1 /
1'
b1 &
#205
0'
#209
b100 $
b100 *
b10100 (
#210
b0 +
b0 ,
b1 -
b10 !
b10 /
b11 3
b100 1
1'
b10 &
#215
0'
#217
b0 2
#219
b101 $
b101 *
b10101 (
#220
b1 +
b101 1
b1 6
b0 3
b11 !
b11 /
1'
b11 &
#225
0'
#228
b1 4
#229
b110 $
b110 *
b10110 (
#230
b0 +
b1 ,
b100 !
b100 /
b1 3
b110 1
1'
b100 &
#235
0'
#237
b1 2
#239
b111 $
b111 *
b10111 (
#240
b1 +
b111 1
b10 3
b101 !
b101 /
1'
b101 &
#245
0'
#249
b1000 $
b1000 *
b11000 (
#250
b0 +
b0 ,
b0 -
b1 .
b110 !
b110 /
b11 3
b1000 1
1'
b110 &
#255
0'
#257
b0 2
b1 5
#259
b1001 $
b1001 *
b11001 (
#260
b1 +
b1001 1
b10 6
b0 3
b111 !
b111 /
1'
b111 &
#265
0'
#268
b10 4
#269
b1010 $
b1010 *
b11010 (
#270
b0 +
b1 ,
b1000 !
b1000 /
b1 3
b1010 1
1'
b1000 &
#275
0'
#277
b1 2
#279
b1011 $
b1011 *
b11011 (
#280
b1 +
b1011 1
b10 3
b1001 !
b1001 /
1'
b1001 &
#285
0'
#289
b1100 $
b1100 *
b11100 (
#290
b0 +
b0 ,
b1 -
b1010 !
b1010 /
b11 3
b1100 1
1'
b1010 &
#295
0'
#297
b0 2
#299
b1101 $
b1101 *
b11101 (
#300
b1 +
b1101 1
b11 6
b0 3
b1011 !
b1011 /
1'
b1011 &
#305
0'
#308
b11 4
#309
b1110 $
b1110 *
b11110 (
#310
b0 +
b1 ,
b1100 !
b1100 /
b1 3
b1110 1
1'
b1100 &
#315
0'
#317
b1 2
#319
b1111 $
b1111 *
b11111 (
#320
b1 +
b1111 1
b10 3
b1101 !
b1101 /
1'
b1101 &
#325
0'
#329
b10 "
b10 )
b0 $
b0 *
b100000 (
#330
b0 .
b0 -
b0 ,
b0 +
b1110 !
b1110 /
b11 3
b0 1
b10 0
1'
b1110 &
#335
0'
#337
b0 5
b0 2
#339
b1 $
b1 *
b100001 (
#340
b10 +
b1 1
b0 6
b0 3
b1111 !
b1111 /
1'
b1111 &
#345
0'
#347
b1 2
#348
b0 4
#349
b10 $
b10 *
b100010 (
#350
b0 +
b10 ,
b0 !
b0 /
b10 3
b10 1
1'
b0 &
#355
0'
#357
b10 2
#359
b11 $
b11 *
b100011 (
#360
b10 +
b11 1
b100 3
b10 !
b10 /
1'
b10 &
#365
0'
#367
b11 2
#368
b1 4
#369
b100 $
b100 *
b100100 (
#370
b0 +
b0 ,
b10 -
b100 !
b100 /
b110 3
b100 1
1'
b100 &
#375
0'
#377
b0 2
b1 5
#379
b101 $
b101 *
b100101 (
#380
b10 +
b101 1
b10 6
b0 3
b110 !
b110 /
1'
b110 &
#385
0'
#387
b1 2
#388
b10 4
#389
b110 $
b110 *
b100110 (
#390
b0 +
b10 ,
b1000 !
b1000 /
b10 3
b110 1
1'
b1000 &
#395
0'
#397
b10 2
#399
b111 $
b111 *
b100111 (
#400
b10 +
b111 1
b100 3
b1010 !
b1010 /
1'
b1010 &
#405
0'
#407
b11 2
#408
b11 4
#409
b1000 $
b1000 *
b101000 (
#410
b0 +
b0 ,
b0 -
b10 .
b1100 !
b1100 /
b110 3
b1000 1
1'
b1100 &
#415
0'
#417
b0 2
b10 5
#419
b1001 $
b1001 *
b101001 (
#420
b10 +
b1001 1
b100 6
b0 3
b1110 !
b1110 /
1'
b1110 &
#425
0'
#427
b1 2
#428
b100 4
#429
b1010 $
b1010 *
b101010 (
#430
b0 +
b10 ,
b10000 !
b10000 /
b10 3
b1010 1
1'
b10000 &
#435
0'
#437
b10 2
#439
b1011 $
b1011 *
b101011 (
#440
b10 +
b1011 1
b100 3
b10010 !
b10010 /
1'
b10010 &
#445
0'
#447
b11 2
#448
b101 4
#449
b1100 $
b1100 *
b101100 (
#450
b0 +
b0 ,
b10 -
b10100 !
b10100 /
b110 3
b1100 1
1'
b10100 &
#455
0'
#457
b0 2
b11 5
#459
b1101 $
b1101 *
b101101 (
#460
b10 +
b1101 1
b110 6
b0 3
b10110 !
b10110 /
1'
b10110 &
#465
0'
#467
b1 2
#468
b110 4
#469
b1110 $
b1110 *
b101110 (
#470
b0 +
b10 ,
b11000 !
b11000 /
b10 3
b1110 1
1'
b11000 &
#475
0'
#477
b10 2
#479
b1111 $
b1111 *
b101111 (
#480
b10 +
b1111 1
b100 3
b11010 !
b11010 /
1'
b11010 &
#485
0'
#487
b11 2
#488
b111 4
#489
b11 "
b11 )
b0 $
b0 *
b110000 (
#490
b0 .
b0 -
b0 ,
b0 +
b11100 !
b11100 /
b110 3
b0 1
b11 0
1'
b11100 &
#495
0'
#497
b0 5
b0 2
#499
b1 $
b1 *
b110001 (
#500
b11 +
b1 1
b0 6
b0 3
b11110 !
b11110 /
1'
b11110 &
#505
0'
#507
b1 2
#508
b0 4
#509
b10 $
b10 *
b110010 (
#510
b0 +
b11 ,
b0 !
b0 /
b11 3
b10 1
1'
b0 &
#515
0'
#517
b11 2
#519
b11 $
b11 *
b110011 (
#520
b11 +
b11 1
b110 3
b11 !
b11 /
1'
b11 &
#525
0'
#527
b100 2
#528
b1 4
#529
b100 $
b100 *
b110100 (
#530
b0 +
b0 ,
b11 -
b110 !
b110 /
b1001 3
b100 1
1'
b110 &
#535
0'
#537
b0 2
b1 5
#538
b10 4
#539
b101 $
b101 *
b110101 (
#540
b11 +
b101 1
b11 6
b0 3
b1001 !
b1001 /
1'
b1001 &
#545
0'
#547
b1 2
#548
b11 4
#549
b110 $
b110 *
b110110 (
#550
b0 +
b11 ,
b1100 !
b1100 /
b11 3
b110 1
1'
b1100 &
#555
0'
#557
b11 2
#559
b111 $
b111 *
b110111 (
#560
b11 +
b111 1
b110 3
b1111 !
b1111 /
1'
b1111 &
#565
0'
#567
b100 2
#568
b100 4
#569
b1000 $
b1000 *
b111000 (
#570
b0 +
b0 ,
b0 -
b11 .
b10010 !
b10010 /
b1001 3
b1000 1
1'
b10010 &
#575
0'
#577
b0 2
b11 5
#578
b101 4
#579
b1001 $
b1001 *
b111001 (
#580
b11 +
b1001 1
b110 6
b0 3
b10101 !
b10101 /
1'
b10101 &
#585
0'
#587
b1 2
#588
b110 4
#589
b1010 $
b1010 *
b111010 (
#590
b0 +
b11 ,
b11000 !
b11000 /
b11 3
b1010 1
1'
b11000 &
#595
0'
#597
b11 2
#599
b1011 $
b1011 *
b111011 (
#600
b11 +
b1011 1
b110 3
b11011 !
b11011 /
1'
b11011 &
#605
0'
#607
b100 2
#608
b111 4
#609
b1100 $
b1100 *
b111100 (
#610
b0 +
b0 ,
b11 -
b11110 !
b11110 /
b1001 3
b1100 1
1'
b11110 &
#615
0'
#617
b0 2
b100 5
#618
b1000 4
#619
b1101 $
b1101 *
b111101 (
#620
b11 +
b1101 1
b1001 6
b0 3
b100001 !
b100001 /
1'
b100001 &
#625
0'
#627
b1 2
#628
b1001 4
#629
b1110 $
b1110 *
b111110 (
#630
b0 +
b11 ,
b100100 !
b100100 /
b11 3
b1110 1
1'
b100100 &
#635
0'
#637
b11 2
#639
b1111 $
b1111 *
b111111 (
#640
b11 +
b1111 1
b110 3
b100111 !
b100111 /
1'
b100111 &
#645
0'
#647
b100 2
#648
b1010 4
#649
b100 "
b100 )
b0 $
b0 *
b1000000 (
#650
b0 .
b0 -
b0 ,
b0 +
b101010 !
b101010 /
b1001 3
b0 1
b100 0
1'
b101010 &
#655
0'
#657
b0 5
b0 2
#658
b1011 4
#659
b1 $
b1 *
b1000001 (
#660
b100 +
b1 1
b0 6
b0 3
b101101 !
b101101 /
1'
b101101 &
#665
0'
#667
b10 2
#668
b0 4
#669
b10 $
b10 *
b1000010 (
#670
b0 +
b100 ,
b0 !
b0 /
b100 3
b10 1
1'
b0 &
#675
0'
#677
b100 2
#678
b1 4
#679
b11 $
b11 *
b1000011 (
#680
b100 +
b11 1
b1000 3
b100 !
b100 /
1'
b100 &
#685
0'
#687
b110 2
#688
b10 4
#689
b100 $
b100 *
b1000100 (
#690
b0 +
b0 ,
b100 -
b1000 !
b1000 /
b1100 3
b100 1
1'
b1000 &
#695
0'
#697
b0 2
b10 5
#698
b11 4
#699
b101 $
b101 *
b1000101 (
#700
b100 +
b101 1
b100 6
b0 3
b1100 !
b1100 /
1'
b1100 &
#705
0'
#707
b10 2
#708
b100 4
#709
b110 $
b110 *
b1000110 (
#710
b0 +
b100 ,
b10000 !
b10000 /
b100 3
b110 1
1'
b10000 &
#715
0'
#717
b100 2
#718
b101 4
#719
b111 $
b111 *
b1000111 (
#720
b100 +
b111 1
b1000 3
b10100 !
b10100 /
1'
b10100 &
#725
0'
#727
b110 2
#728
b110 4
#729
b1000 $
b1000 *
b1001000 (
#730
b0 +
b0 ,
b0 -
b100 .
b11000 !
b11000 /
b1100 3
b1000 1
1'
b11000 &
#735
0'
#737
b0 2
b100 5
#738
b111 4
#739
b1001 $
b1001 *
b1001001 (
#740
b100 +
b1001 1
b1000 6
b0 3
b11100 !
b11100 /
1'
b11100 &
#745
0'
#747
b10 2
#748
b1000 4
#749
b1010 $
b1010 *
b1001010 (
#750
b0 +
b100 ,
b100000 !
b100000 /
b100 3
b1010 1
1'
b100000 &
#755
0'
#757
b100 2
#758
b1001 4
#759
b1011 $
b1011 *
b1001011 (
#760
b100 +
b1011 1
b1000 3
b100100 !
b100100 /
1'
b100100 &
#765
0'
#767
b110 2
#768
b1010 4
#769
b1100 $
b1100 *
b1001100 (
#770
b0 +
b0 ,
b100 -
b101000 !
b101000 /
b1100 3
b1100 1
1'
b101000 &
#775
0'
#777
b0 2
b110 5
#778
b1011 4
#779
b1101 $
b1101 *
b1001101 (
#780
b100 +
b1101 1
b1100 6
b0 3
b101100 !
b101100 /
1'
b101100 &
#785
0'
#787
b10 2
#788
b1100 4
#789
b1110 $
b1110 *
b1001110 (
#790
b0 +
b100 ,
b110000 !
b110000 /
b100 3
b1110 1
1'
b110000 &
#795
0'
#797
b100 2
#798
b1101 4
#799
b1111 $
b1111 *
b1001111 (
#800
b100 +
b1111 1
b1000 3
b110100 !
b110100 /
1'
b110100 &
#805
0'
#807
b110 2
#808
b1110 4
#809
b101 "
b101 )
b0 $
b0 *
b1010000 (
#810
b0 .
b0 -
b0 ,
b0 +
b111000 !
b111000 /
b1100 3
b0 1
b101 0
1'
b111000 &
#815
0'
#817
b0 5
b0 2
#818
b1111 4
#819
b1 $
b1 *
b1010001 (
#820
b101 +
b1 1
b0 6
b0 3
b111100 !
b111100 /
1'
b111100 &
#825
0'
#827
b10 2
#828
b0 4
#829
b10 $
b10 *
b1010010 (
#830
b0 +
b101 ,
b0 !
b0 /
b101 3
b10 1
1'
b0 &
#835
0'
#837
b101 2
#838
b1 4
#839
b11 $
b11 *
b1010011 (
#840
b101 +
b11 1
b1010 3
b101 !
b101 /
1'
b101 &
#845
0'
#847
b111 2
#848
b10 4
#849
b100 $
b100 *
b1010100 (
#850
b0 +
b0 ,
b101 -
b1010 !
b1010 /
b1111 3
b100 1
1'
b1010 &
#855
0'
#857
b0 2
b10 5
#858
b11 4
#859
b101 $
b101 *
b1010101 (
#860
b101 +
b101 1
b101 6
b0 3
b1111 !
b1111 /
1'
b1111 &
#865
0'
#867
b10 2
#868
b101 4
#869
b110 $
b110 *
b1010110 (
#870
b0 +
b101 ,
b10100 !
b10100 /
b101 3
b110 1
1'
b10100 &
#875
0'
#877
b101 2
#878
b110 4
#879
b111 $
b111 *
b1010111 (
#880
b101 +
b111 1
b1010 3
b11001 !
b11001 /
1'
b11001 &
#885
0'
#887
b111 2
#888
b111 4
#889
b1000 $
b1000 *
b1011000 (
#890
b0 +
b0 ,
b0 -
b101 .
b11110 !
b11110 /
b1111 3
b1000 1
1'
b11110 &
#895
0'
#897
b0 2
b101 5
#898
b1000 4
#899
b1001 $
b1001 *
b1011001 (
#900
b101 +
b1001 1
b1010 6
b0 3
b100011 !
b100011 /
1'
b100011 &
#905
0'
#907
b10 2
#908
b1010 4
#909
b1010 $
b1010 *
b1011010 (
#910
b0 +
b101 ,
b101000 !
b101000 /
b101 3
b1010 1
1'
b101000 &
#915
0'
#917
b101 2
#918
b1011 4
#919
b1011 $
b1011 *
b1011011 (
#920
b101 +
b1011 1
b1010 3
b101101 !
b101101 /
1'
b101101 &
#925
0'
#927
b111 2
#928
b1100 4
#929
b1100 $
b1100 *
b1011100 (
#930
b0 +
b0 ,
b101 -
b110010 !
b110010 /
b1111 3
b1100 1
1'
b110010 &
#935
0'
#937
b0 2
b111 5
#938
b1101 4
#939
b1101 $
b1101 *
b1011101 (
#940
b101 +
b1101 1
b1111 6
b0 3
b110111 !
b110111 /
1'
b110111 &
#945
0'
#947
b10 2
#948
b1111 4
#949
b1110 $
b1110 *
b1011110 (
#950
b0 +
b101 ,
b111100 !
b111100 /
b101 3
b1110 1
1'
b111100 &
#955
0'
#957
b101 2
#958
b10000 4
#959
b1111 $
b1111 *
b1011111 (
#960
b101 +
b1111 1
b1010 3
b1000001 !
b1000001 /
1'
b1000001 &
#965
0'
#967
b111 2
#968
b10001 4
#969
b110 "
b110 )
b0 $
b0 *
b1100000 (
#970
b0 .
b0 -
b0 ,
b0 +
b1000110 !
b1000110 /
b1111 3
b0 1
b110 0
1'
b1000110 &
#975
0'
#977
b0 5
b0 2
#978
b10010 4
#979
b1 $
b1 *
b1100001 (
#980
b110 +
b1 1
b0 6
b0 3
b1001011 !
b1001011 /
1'
b1001011 &
#985
0'
#987
b11 2
#988
b0 4
#989
b10 $
b10 *
b1100010 (
#990
b0 +
b110 ,
b0 !
b0 /
b110 3
b10 1
1'
b0 &
#995
0'
#997
b110 2
#998
b1 4
#999
b11 $
b11 *
b1100011 (
#1000
b110 +
b11 1
b1100 3
b110 !
b110 /
1'
b110 &
#1005
0'
#1007
b1001 2
#1008
b11 4
#1009
b100 $
b100 *
b1100100 (
#1010
b0 +
b0 ,
b110 -
b1100 !
b1100 /
b10010 3
b100 1
1'
b1100 &
#1015
0'
#1017
b0 2
b11 5
#1018
b100 4
#1019
b101 $
b101 *
b1100101 (
#1020
b110 +
b101 1
b110 6
b0 3
b10010 !
b10010 /
1'
b10010 &
#1025
0'
#1027
b11 2
#1028
b110 4
#1029
b110 $
b110 *
b1100110 (
#1030
b0 +
b110 ,
b11000 !
b11000 /
b110 3
b110 1
1'
b11000 &
#1035
0'
#1037
b110 2
#1038
b111 4
#1039
b111 $
b111 *
b1100111 (
#1040
b110 +
b111 1
b1100 3
b11110 !
b11110 /
1'
b11110 &
#1045
0'
#1047
b1001 2
#1048
b1001 4
#1049
b1000 $
b1000 *
b1101000 (
#1050
b0 +
b0 ,
b0 -
b110 .
b100100 !
b100100 /
b10010 3
b1000 1
1'
b100100 &
#1055
0'
#1057
b0 2
b110 5
#1058
b1010 4
#1059
b1001 $
b1001 *
b1101001 (
#1060
b110 +
b1001 1
b1100 6
b0 3
b101010 !
b101010 /
1'
b101010 &
#1065
0'
#1067
b11 2
#1068
b1100 4
#1069
b1010 $
b1010 *
b1101010 (
#1070
b0 +
b110 ,
b110000 !
b110000 /
b110 3
b1010 1
1'
b110000 &
#1075
0'
#1077
b110 2
#1078
b1101 4
#1079
b1011 $
b1011 *
b1101011 (
#1080
b110 +
b1011 1
b1100 3
b110110 !
b110110 /
1'
b110110 &
#1085
0'
#1087
b1001 2
#1088
b1111 4
#1089
b1100 $
b1100 *
b1101100 (
#1090
b0 +
b0 ,
b110 -
b111100 !
b111100 /
b10010 3
b1100 1
1'
b111100 &
#1095
0'
#1097
b0 2
b1001 5
#1098
b10000 4
#1099
b1101 $
b1101 *
b1101101 (
#1100
b110 +
b1101 1
b10010 6
b0 3
b1000010 !
b1000010 /
1'
b1000010 &
#1105
0'
#1107
b11 2
#1108
b10010 4
#1109
b1110 $
b1110 *
b1101110 (
#1110
b0 +
b110 ,
b1001000 !
b1001000 /
b110 3
b1110 1
1'
b1001000 &
#1115
0'
#1117
b110 2
#1118
b10011 4
#1119
b1111 $
b1111 *
b1101111 (
#1120
b110 +
b1111 1
b1100 3
b1001110 !
b1001110 /
1'
b1001110 &
#1125
0'
#1127
b1001 2
#1128
b10101 4
#1129
b111 "
b111 )
b0 $
b0 *
b1110000 (
#1130
b0 .
b0 -
b0 ,
b0 +
b1010100 !
b1010100 /
b10010 3
b0 1
b111 0
1'
b1010100 &
#1135
0'
#1137
b0 5
b0 2
#1138
b10110 4
#1139
b1 $
b1 *
b1110001 (
#1140
b111 +
b1 1
b0 6
b0 3
b1011010 !
b1011010 /
1'
b1011010 &
#1145
0'
#1147
b11 2
#1148
b0 4
#1149
b10 $
b10 *
b1110010 (
#1150
b0 +
b111 ,
b0 !
b0 /
b111 3
b10 1
1'
b0 &
#1155
0'
#1157
b111 2
#1158
b1 4
#1159
b11 $
b11 *
b1110011 (
#1160
b111 +
b11 1
b1110 3
b111 !
b111 /
1'
b111 &
#1165
0'
#1167
b1010 2
#1168
b11 4
#1169
b100 $
b100 *
b1110100 (
#1170
b0 +
b0 ,
b111 -
b1110 !
b1110 /
b10101 3
b100 1
1'
b1110 &
#1175
0'
#1177
b0 2
b11 5
#1178
b101 4
#1179
b101 $
b101 *
b1110101 (
#1180
b111 +
b101 1
b111 6
b0 3
b10101 !
b10101 /
1'
b10101 &
#1185
0'
#1187
b11 2
#1188
b111 4
#1189
b110 $
b110 *
b1110110 (
#1190
b0 +
b111 ,
b11100 !
b11100 /
b111 3
b110 1
1'
b11100 &
#1195
0'
#1197
b111 2
#1198
b1000 4
#1199
b111 $
b111 *
b1110111 (
#1200
b111 +
b111 1
b1110 3
b100011 !
b100011 /
1'
b100011 &
#1205
0'
#1207
b1010 2
#1208
b1010 4
#1209
b1000 $
b1000 *
b1111000 (
#1210
b0 +
b0 ,
b0 -
b111 .
b101010 !
b101010 /
b10101 3
b1000 1
1'
b101010 &
#1215
0'
#1217
b0 2
b111 5
#1218
b1100 4
#1219
b1001 $
b1001 *
b1111001 (
#1220
b111 +
b1001 1
b1110 6
b0 3
b110001 !
b110001 /
1'
b110001 &
#1225
0'
#1227
b11 2
#1228
b1110 4
#1229
b1010 $
b1010 *
b1111010 (
#1230
b0 +
b111 ,
b111000 !
b111000 /
b111 3
b1010 1
1'
b111000 &
#1235
0'
#1237
b111 2
#1238
b1111 4
#1239
b1011 $
b1011 *
b1111011 (
#1240
b111 +
b1011 1
b1110 3
b111111 !
b111111 /
1'
b111111 &
#1245
0'
#1247
b1010 2
#1248
b10001 4
#1249
b1100 $
b1100 *
b1111100 (
#1250
b0 +
b0 ,
b111 -
b1000110 !
b1000110 /
b10101 3
b1100 1
1'
b1000110 &
#1255
0'
#1257
b0 2
b1010 5
#1258
b10011 4
#1259
b1101 $
b1101 *
b1111101 (
#1260
b111 +
b1101 1
b10101 6
b0 3
b1001101 !
b1001101 /
1'
b1001101 &
#1265
0'
#1267
b11 2
#1268
b10101 4
#1269
b1110 $
b1110 *
b1111110 (
#1270
b0 +
b111 ,
b1010100 !
b1010100 /
b111 3
b1110 1
1'
b1010100 &
#1275
0'
#1277
b111 2
#1278
b10110 4
#1279
b1111 $
b1111 *
b1111111 (
#1280
b111 +
b1111 1
b1110 3
b1011011 !
b1011011 /
1'
b1011011 &
#1285
0'
#1287
b1010 2
#1288
b11000 4
#1289
b1000 "
b1000 )
b0 $
b0 *
b10000000 (
#1290
b0 .
b0 -
b0 ,
b0 +
b1100010 !
b1100010 /
b10101 3
b0 1
b1000 0
1'
b1100010 &
#1295
0'
#1297
b0 5
b0 2
#1298
b11010 4
#1299
b1 $
b1 *
b10000001 (
#1300
b1000 +
b1 1
b0 6
b0 3
b1101001 !
b1101001 /
1'
b1101001 &
#1305
0'
#1307
b100 2
#1308
b0 4
#1309
b10 $
b10 *
b10000010 (
#1310
b0 +
b1000 ,
b0 !
b0 /
b1000 3
b10 1
1'
b0 &
#1315
0'
#1317
b1000 2
#1318
b10 4
#1319
b11 $
b11 *
b10000011 (
#1320
b1000 +
b11 1
b10000 3
b1000 !
b1000 /
1'
b1000 &
#1325
0'
#1327
b1100 2
#1328
b100 4
#1329
b100 $
b100 *
b10000100 (
#1330
b0 +
b0 ,
b1000 -
b10000 !
b10000 /
b11000 3
b100 1
1'
b10000 &
#1335
0'
#1337
b0 2
b100 5
#1338
b110 4
#1339
b101 $
b101 *
b10000101 (
#1340
b1000 +
b101 1
b1000 6
b0 3
b11000 !
b11000 /
1'
b11000 &
#1345
0'
#1347
b100 2
#1348
b1000 4
#1349
b110 $
b110 *
b10000110 (
#1350
b0 +
b1000 ,
b100000 !
b100000 /
b1000 3
b110 1
1'
b100000 &
#1355
0'
#1357
b1000 2
#1358
b1010 4
#1359
b111 $
b111 *
b10000111 (
#1360
b1000 +
b111 1
b10000 3
b101000 !
b101000 /
1'
b101000 &
#1365
0'
#1367
b1100 2
#1368
b1100 4
#1369
b1000 $
b1000 *
b10001000 (
#1370
b0 +
b0 ,
b0 -
b1000 .
b110000 !
b110000 /
b11000 3
b1000 1
1'
b110000 &
#1375
0'
#1377
b0 2
b1000 5
#1378
b1110 4
#1379
b1001 $
b1001 *
b10001001 (
#1380
b1000 +
b1001 1
b10000 6
b0 3
b111000 !
b111000 /
1'
b111000 &
#1385
0'
#1387
b100 2
#1388
b10000 4
#1389
b1010 $
b1010 *
b10001010 (
#1390
b0 +
b1000 ,
b1000000 !
b1000000 /
b1000 3
b1010 1
1'
b1000000 &
#1395
0'
#1397
b1000 2
#1398
b10010 4
#1399
b1011 $
b1011 *
b10001011 (
#1400
b1000 +
b1011 1
b10000 3
b1001000 !
b1001000 /
1'
b1001000 &
#1405
0'
#1407
b1100 2
#1408
b10100 4
#1409
b1100 $
b1100 *
b10001100 (
#1410
b0 +
b0 ,
b1000 -
b1010000 !
b1010000 /
b11000 3
b1100 1
1'
b1010000 &
#1415
0'
#1417
b0 2
b1100 5
#1418
b10110 4
#1419
b1101 $
b1101 *
b10001101 (
#1420
b1000 +
b1101 1
b11000 6
b0 3
b1011000 !
b1011000 /
1'
b1011000 &
#1425
0'
#1427
b100 2
#1428
b11000 4
#1429
b1110 $
b1110 *
b10001110 (
#1430
b0 +
b1000 ,
b1100000 !
b1100000 /
b1000 3
b1110 1
1'
b1100000 &
#1435
0'
#1437
b1000 2
#1438
b11010 4
#1439
b1111 $
b1111 *
b10001111 (
#1440
b1000 +
b1111 1
b10000 3
b1101000 !
b1101000 /
1'
b1101000 &
#1445
0'
#1447
b1100 2
#1448
b11100 4
#1449
b1001 "
b1001 )
b0 $
b0 *
b10010000 (
#1450
b0 .
b0 -
b0 ,
b0 +
b1110000 !
b1110000 /
b11000 3
b0 1
b1001 0
1'
b1110000 &
#1455
0'
#1457
b0 5
b0 2
#1458
b11110 4
#1459
b1 $
b1 *
b10010001 (
#1460
b1001 +
b1 1
b0 6
b0 3
b1111000 !
b1111000 /
1'
b1111000 &
#1465
0'
#1467
b100 2
#1468
b0 4
#1469
b10 $
b10 *
b10010010 (
#1470
b0 +
b1001 ,
b0 !
b0 /
b1001 3
b10 1
1'
b0 &
#1475
0'
#1477
b1001 2
#1478
b10 4
#1479
b11 $
b11 *
b10010011 (
#1480
b1001 +
b11 1
b10010 3
b1001 !
b1001 /
1'
b1001 &
#1485
0'
#1487
b1101 2
#1488
b100 4
#1489
b100 $
b100 *
b10010100 (
#1490
b0 +
b0 ,
b1001 -
b10010 !
b10010 /
b11011 3
b100 1
1'
b10010 &
#1495
0'
#1497
b0 2
b100 5
#1498
b110 4
#1499
b101 $
b101 *
b10010101 (
#1500
b1001 +
b101 1
b1001 6
b0 3
b11011 !
b11011 /
1'
b11011 &
#1505
0'
#1507
b100 2
#1508
b1001 4
#1509
b110 $
b110 *
b10010110 (
#1510
b0 +
b1001 ,
b100100 !
b100100 /
b1001 3
b110 1
1'
b100100 &
#1515
0'
#1517
b1001 2
#1518
b1011 4
#1519
b111 $
b111 *
b10010111 (
#1520
b1001 +
b111 1
b10010 3
b101101 !
b101101 /
1'
b101101 &
#1525
0'
#1527
b1101 2
#1528
b1101 4
#1529
b1000 $
b1000 *
b10011000 (
#1530
b0 +
b0 ,
b0 -
b1001 .
b110110 !
b110110 /
b11011 3
b1000 1
1'
b110110 &
